__init__.py
magiclip.py
main.py
magiclip-0.2.0.dist-info/LICENSE
magiclip-0.2.0.dist-info/METADATA
magiclip-0.2.0.dist-info/WHEEL
magiclip-0.2.0.dist-info/entry_points.txt
magiclip-0.2.0.dist-info/top_level.txt
magiclip-0.2.0.dist-info/RECORD
