Metadata-Version: 2.1
Name: magiclip
Version: 0.2.0
Summary: Magic Clipboard for smart operations
Author-email: Pedro Mayorga <ppmayorga80@gmail.com>
Classifier: Programming Language :: Python :: 3
Classifier: License :: OSI Approved :: MIT License
Classifier: Operating System :: OS Independent
Requires-Python: >=3.7
License-File: LICENSE
Requires-Dist: docopt ~=0.6.2
Requires-Dist: pyperclip ~=1.8.2
Requires-Dist: python-dotenv ~=1.0.0
Requires-Dist: tabulate ~=0.9.0
Requires-Dist: tqdm ~=4.66.1
